post_orm/__init__.py
post_orm/example.py
post_orm-0.0.4.dist-info/LICENSE
post_orm-0.0.4.dist-info/METADATA
post_orm-0.0.4.dist-info/WHEEL
post_orm-0.0.4.dist-info/top_level.txt
post_orm-0.0.4.dist-info/RECORD
