Metadata-Version: 2.1
Name: post-orm
Version: 0.0.4
Summary: A minimal ORM for PostgreSQL
Author-email: Jonas Sandström <jonasliu89@gmail.com>
Project-URL: Homepage, https://github.com/jonasps/post_orm
Classifier: Programming Language :: Python :: 3
Classifier: License :: OSI Approved :: MIT License
Classifier: Operating System :: OS Independent
Requires-Python: >=3.7
License-File: LICENSE
Requires-Dist: psycopg2-binary (>=2.9.5)
Provides-Extra: test
Requires-Dist: pytest (>=7.1.3) ; extra == 'test'
